typedstruct.py
typedstruct-0.1.0.dist-info/LICENSE.txt
typedstruct-0.1.0.dist-info/WHEEL
typedstruct-0.1.0.dist-info/METADATA
typedstruct-0.1.0.dist-info/RECORD
