Metadata-Version: 2.1
Name: typedstruct
Version: 0.1.0
Summary: A wrapper around the struct library with support for PEP 484 types.
Home-page: https://github.com/luizribeiro/typedstruct
License: MIT
Keywords: typing,structs
Author: Luiz Ribeiro
Author-email: luizribeiro@gmail.com
Requires-Python: >=3.7,<4.0
Classifier: Development Status :: 3 - Alpha
Classifier: Intended Audience :: Developers
Classifier: License :: OSI Approved :: MIT License
Classifier: Operating System :: OS Independent
Classifier: Programming Language :: Python :: 3
Classifier: Programming Language :: Python :: 3.7
Classifier: Programming Language :: Python :: 3.8
Classifier: Topic :: Software Development :: Libraries :: Python Modules
Classifier: Typing :: Typed
Project-URL: Repository, https://github.com/luizribeiro/typedstruct
